<?xml version="1.0"?>
<!DOCTYPE hibernate-mapping
	PUBLIC "-//Hibernate/Hibernate Mapping DTD//EN"
	"http://hibernate.sourceforge.net/hibernate-mapping-3.0.dtd">

<hibernate-mapping>

	<class name="org.yawlfoundation.yawl.worklet.support.WorkletEvent"
           table="Worklet_EventLog">

       <id name="_id" column="eventid" type="long" access="field">
   		    <generator class="assigned"/>
       </id>
		
       <property name="_event"        column="eventName"/>
       <property name="_caseId"       column="caseId"/>
       <property name="_specId"       column="specId"/>
       <property name="_taskId"       column="taskId"/>
       <property name="_parentCaseId" column="parentCaseId"/>
       <property name="_stamp"        column="tStamp"/>
       <property name="_xType"        column="xType" type="int"/>

    </class>
	
</hibernate-mapping>